{"0":{"title":"Product Beta","price":"607","subject":"Lorem ipsum dolor sunt in culpa qui officia deserunt mollit anim id est laborum.","color":"blue"},"1":{"title":"Product Alpha","price":"511","subject":"Lorem ipsum dolor sunt in culpa qui officia deserunt mollit anim id est laborum.","color":"red"},"2":{"title":"Product Zeta","price":"55","subject":"Lorem ipsum dolor sunt in culpa qui officia deserunt mollit anim id est laborum.","color":"green"},"3":{"title":"Product Omega","price":"107","subject":"Lorem ipsum dolor sunt in culpa qui officia deserunt mollit anim id est laborum.","color":"gray"},"4":{"title":"Product Gamma","price":"800","subject":"Lorem ipsum dolor sunt in culpa qui officia deserunt mollit anim id est laborum.","color":"red"}}